secret_guardian/__init__.py
secret_guardian/__main__.py
secret_guardian/cli.py
secret_guardian/exceptions.py
secret_guardian/patterns.py
secret_guardian/scanner.py
secret_guardian-0.1.0.dist-info/METADATA
secret_guardian-0.1.0.dist-info/WHEEL
secret_guardian-0.1.0.dist-info/entry_points.txt
secret_guardian-0.1.0.dist-info/RECORD
