Metadata-Version: 2.1
Name: secret-guardian
Version: 0.1.0
Summary: A Python library for detecting hardcoded secrets and API keys in code repositories
Home-page: https://github.com/panyu1512/secret-guardian
License: MIT
Keywords: security,secrets,api-keys,code-scanning
Author: panyu1512
Author-email: kikeferreragius1997@gmail.com
Requires-Python: >=3.8.1,<4.0.0
Classifier: Development Status :: 4 - Beta
Classifier: Intended Audience :: Developers
Classifier: License :: OSI Approved :: MIT License
Classifier: Programming Language :: Python :: 3
Classifier: Programming Language :: Python :: 3.9
Classifier: Programming Language :: Python :: 3.10
Classifier: Programming Language :: Python :: 3.11
Classifier: Programming Language :: Python :: 3.12
Classifier: Programming Language :: Python :: 3.13
Classifier: Programming Language :: Python :: 3.8
Classifier: Topic :: Security
Classifier: Topic :: Software Development :: Libraries :: Python Modules
Requires-Dist: click (>=8.1.7,<9.0.0)
Requires-Dist: gitpython (>=3.1.40,<4.0.0)
Requires-Dist: python-dotenv (>=1.0.0,<2.0.0)
Project-URL: Repository, https://github.com/panyu1512/secret-guardian
